[{"txs": [{"target": "0x::ibc", "value": 0, "data": {"method": "connect", "chain": "agoric"}, "state": 1, "gas_used": 0, "out_actions": [], "time": 2080.0, "block": 0}, {"target": "0x::ibc", "value": 0, "data": {"method": "connect", "chain": "arkh"}, "state": 1, "gas_used": 0, "out_actions": [], "time": 2080.0, "block": 0}, {"target": "0x::ibc", "value": 0, "data": {"method": "connect", "chain": "akash"}, "state": 1, "gas_used": 0, "out_actions": [], "time": 2080.0, "block": 0}, {"target": "0x::ibc", "value": 0, "data": {"method": "connect", "chain": "axelar"}, "state": 1, "gas_used": 0, "out_actions": [], "time": 2080.0, "block": 0}, {"target": "0x::ibc", "value": 0, "data": {"method": "connect", "chain": "kichain"}, "state": 1, "gas_used": 0, "out_actions": [], "time": 2080.0, "block": 0}, {"target": "0x::ibc", "value": 0, "data": {"method": "connect", "chain": "assetmantle"}, "state": 1, "gas_used": 0, "out_actions": [], "time": 2080.0, "block": 0}, {"target": "0x::ibc", "value": 0, "data": {"method": "connect", "chain": "osmosis"}, "state": 1, "gas_used": 0, "out_actions": [], "time": 2080.0, "block": 0}, {"target": "0x::ibc", "value": 0, "data": {"method": "connect", "chain": "beezee"}, "state": 1, "gas_used": 0, "out_actions": [], "time": 2080.0, "block": 0}, {"target": "0x::ibc", "value": 0, "data": {"method": "connect", "chain": "kujira"}, "state": 1, "gas_used": 0, "out_actions": [], "time": 2080.0, "block": 0}, {"target": "0x::ibc", "value": 0, "data": {"method": "connect", "chain": "8ball"}, "state": 1, "gas_used": 0, "out_actions": [], "time": 2080.0, "block": 0}], "seq_no": 0, "time": 2080.0}, {"txs": [{"target": "0x::ibc", "value": 0, "data": {"method": "connect", "chain": "cheqd"}, "state": 1, "gas_used": 0, "out_actions": [], "time": 2090.0, "block": 1}, {"target": "0x::ibc", "value": 0, "data": {"method": "connect", "chain": "terra2"}, "state": 1, "gas_used": 0, "out_actions": [], "time": 2090.0, "block": 1}], "seq_no": 1, "time": 2090.0}]